humanstxt.py
setup.py
humanstxt.egg-info/PKG-INFO
humanstxt.egg-info/SOURCES.txt
humanstxt.egg-info/dependency_links.txt
humanstxt.egg-info/top_level.txt
test/test.py